valid_input/__init__.py
valid_input/tests.py
valid_input/tools.py
valid_input-1.0.0.dist-info/LICENSE
valid_input-1.0.0.dist-info/METADATA
valid_input-1.0.0.dist-info/WHEEL
valid_input-1.0.0.dist-info/top_level.txt
valid_input-1.0.0.dist-info/RECORD
