Metadata-Version: 2.1
Name: valid_input
Version: 1.0.0
Summary: A simple lightweight library to avoid writting common input checks
Home-page: https://github.com/hectorxlxs
Author: Héctor Martínez González
Author-email: hector.xilxes@gmail.com
License: MIT
License-File: LICENSE
